Workbook

Sheet Resumo
A1: Resumo executivo - custo atual x cenários PJ
A3: Indicador | B3: Valor | D3: Cenário | E3: Economia anual | F3: Economia %
A4: Remuneração econômica mensal atual | B4: =Premissas!B18 -> 24008 | D4: PJ 12x + benefícios | E4: =Cenarios!C13 -> 36799.2 | F4: =Cenarios!C15 -> 0.11088391
A5: Custo anual atual da empresa | B5: =Cenarios!B11 -> 331871.4 | D5: PJ 13x + benefícios | E5: =Cenarios!D13 -> 12791.2 | F5: =Cenarios!D15 -> 0.03854264
A6: Custo mensal equivalente atual | B6: =Cenarios!B12 -> 27655.95 | D6: PJ 13x + 1/3 férias + benefícios | E6: =Cenarios!E13 -> 4788.5333 | F6: =Cenarios!E15 -> 0.014428882
A7: Custo PJ 12x + benefícios | B7: =Cenarios!C11 -> 295072.2
A8: Custo PJ 13x + benefícios | B8: =Cenarios!D11 -> 319080.2
A10: Leitura rápida
A11: • O custo anual atual inclui salário registrado, valor adicional, FGTS, 13º, 1/3 de férias e a parcela de saúde/odonto paga pela empresa.
A12: • O cenário PJ 12x preserva a remuneração mensal econômica e os benefícios, mas elimina FGTS, 13º e 1/3 de férias.
A13: • O cenário PJ 13x acrescenta uma 13ª remuneração integral sobre os R$ 24.008,00.
A14: • O cenário PJ 13x + 1/3 adiciona também um equivalente de 1/3 sobre a remuneração econômica integral.
A15: • Use a aba Simulador para alterar fee, número de pagamentos, férias/recesso, benefícios, carro e bônus.

Sheet Premissas
A1: Premissas do modelo
A3: Premissa | B3: Valor | C3: Unidade | D3: Observação / Fonte
A4: Salário bruto registrado | B4: 15333 | C4: R$/mês | D4: Holerite março/2026
A5: Remuneração adicional 'por fora' | B5: 8675 | C5: R$/mês | D5: Informado pelo usuário
A6: FGTS | B6: 0.08 | C6: % | D6: Incidência sobre remuneração registrada / 13º / 1/3 férias
A7: Plano de saúde - custo total informado | B7: 1609.54 | C7: R$/mês | D7: Holerite março/2026
A8: Plano de saúde - desconto do funcionário | B8: 1045.43 | C8: R$/mês | D8: Holerite março/2026
A9: Plano odontológico - custo total informado | B9: 87.72 | C9: R$/mês | D9: Holerite março/2026
A10: Plano odontológico - desconto do funcionário | B10: 70.48 | C10: R$/mês | D10: Holerite março/2026
A11: Coparticipação saúde descontada do funcionário | B11: 193.42 | C11: R$/mês | D11: Holerite março/2026
A12: Número de salários CLT no ano | B12: 12 | C12: x | D12: Salário mensal normal
A13: 13º CLT | B13: 1 | C13: x salário | D13: Um salário adicional por ano
A14: Adicional constitucional de férias | B14: 0.33333333 | C14: % do salário | D14: Custo adicional ao salário já contido nos 12 meses
A15: CPP/INSS patronal adicional fora do DAS | B15: 0 | C15: % | D15: Premissa: Simples Nacional fora do Anexo IV
A17: Cálculos derivados | B17: Valor | C17: Unidade | D17: Fórmula
A18: Remuneração econômica mensal | B18: =B4+B5 -> 24008 | C18: R$/mês | D18: Salário registrado + valor adicional
A19: Custo empresa - saúde | B19: =B7-B8 -> 564.11 | C19: R$/mês | D19: Custo total saúde - desconto funcionário
A20: Custo empresa - odontológico | B20: =B9-B10 -> 17.24 | C20: R$/mês | D20: Custo total odonto - desconto funcionário
A21: Benefícios mensais pagos pela empresa | B21: =B19+B20 -> 581.35 | C21: R$/mês | D21: Saúde + odonto pagos pela empresa
A22: FGTS mensal sobre salário registrado | B22: =B4*B6 -> 1226.64 | C22: R$/mês | D22: Salário registrado × 8%

Sheet Cenarios
A1: Comparação de cenários - custo anual da empresa
A3: Componente | B3: Atual CLT + extra | C3: PJ 12x + benefícios | D3: PJ 13x + benefícios | E3: PJ 13x + 1/3 férias + benefícios | F3: Observação | G3: Base | H3: Unidade
A4: 12 remunerações mensais | B4: =Premissas!B4*12+Premissas!B5*12 -> 288096 | C4: =Premissas!B18*12 -> 288096 | D4: =Premissas!B18*12 -> 288096 | E4: =Premissas!B18*12 -> 288096 | F4: Atual: registrado + adicional; PJ: remuneração econômica integral | G4: 12 meses | H4: R$/ano
A5: 13ª remuneração | B5: =Premissas!B4 -> 15333 | C5: 0 | D5: =Premissas!B18 -> 24008 | E5: =Premissas!B18 -> 24008 | F5: Atual: só sobre registrado; PJ conforme cenário | G5: 1 pagamento | H5: R$/ano
A6: 1/3 de férias / equivalente | B6: =Premissas!B4*Premissas!B14 -> 5111 | C6: 0 | D6: 0 | E6: =Premissas!B18*Premissas!B14 -> 8002.6667 | F6: Atual: só sobre registrado; PJ conforme cenário | G6: 1/3 | H6: R$/ano
A7: FGTS mensal (12 meses) | B7: =Premissas!B22*12 -> 14719.68 | C7: 0 | D7: 0 | E7: 0 | F7: Somente CLT | G7: 8% | H7: R$/ano
A8: FGTS sobre 13º | B8: =Premissas!B4*Premissas!B6 -> 1226.64 | C8: 0 | D8: 0 | E8: 0 | F8: Somente CLT | G8: 8% | H8: R$/ano
A9: FGTS sobre 1/3 de férias | B9: =Premissas!B4*Premissas!B14*Premissas!B6 -> 408.88 | C9: 0 | D9: 0 | E9: 0 | F9: Somente CLT | G9: 8% | H9: R$/ano
A10: Saúde + odontológico (12 meses) | B10: =Premissas!B21*12 -> 6976.2 | C10: =Premissas!B21*12 -> 6976.2 | D10: =Premissas!B21*12 -> 6976.2 | E10: =Premissas!B21*12 -> 6976.2 | F10: Mantidos iguais em todos os cenários | G10: 12 meses | H10: R$/ano
A11: CUSTO ANUAL TOTAL | B11: =SUM(B4:B10) -> 331871.4 | C11: =SUM(C4:C10) -> 295072.2 | D11: =SUM(D4:D10) -> 319080.2 | E11: =SUM(E4:E10) -> 327082.87 | F11: Soma dos componentes anuais | G11: Total | H11: R$/ano
A12: CUSTO MENSAL EQUIVALENTE | B12: =B11/12 -> 27655.95 | C12: =C11/12 -> 24589.35 | D12: =D11/12 -> 26590.017 | E12: =E11/12 -> 27256.906 | F12: Custo anual ÷ 12 | G12: Média | H12: R$/mês
A13: ECONOMIA ANUAL vs. atual | B13: =0 -> 0 | C13: =$B$11-C11 -> 36799.2 | D13: =$B$11-D11 -> 12791.2 | E13: =$B$11-E11 -> 4788.5333 | F13: Custo atual - cenário | G13: Diferença | H13: R$/ano
A14: ECONOMIA MENSAL EQUIVALENTE | B14: =0 -> 0 | C14: =C13/12 -> 3066.6 | D14: =D13/12 -> 1065.9333 | E14: =E13/12 -> 399.04444 | F14: Economia anual ÷ 12 | G14: Média | H14: R$/mês
A15: ECONOMIA % vs. atual | B15: =0 -> 0 | C15: =C13/$B$11 -> 0.11088391 | D15: =D13/$B$11 -> 0.03854264 | E15: =E13/$B$11 -> 0.014428882 | F15: Economia anual ÷ custo atual | G15: Percentual | H15: %

Sheet Simulador
A1: Simulador de proposta PJ
A3: Entrada / premissa | B3: Valor | C3: Unidade | D3: Resultado | E3: Valor | F3: Observação
A4: Fee mensal PJ | B4: =Premissas!B18 -> 24008 | C4: R$/mês | D4: Custo anual com fees | E4: =B4*B5 -> 312104 | F4: Digite o valor mensal proposto
A5: Número de pagamentos anuais | B5: 13 | C5: x | D5: Adicional anual férias/recesso | E5: =B4*B6 -> 0 | F5: Ex.: 12, 13 ou 14
A6: Adicional de férias / recesso | B6: 0 | C6: % do fee | D6: Benefícios mensais anualizados | E6: =(B7+B8+B9+B10)*12 -> 6976.2 | F6: 0% = só recesso remunerado; 33,33% = equivalente ao 1/3
A7: Plano saúde - custo empresa | B7: =Premissas!B19 -> 564.11 | C7: R$/mês | D7: Bônus anual | E7: =B11 -> 0 | F7: Pode manter o custo atual ou simular outro
A8: Plano odonto - custo empresa | B8: =Premissas!B20 -> 17.24 | C8: R$/mês | D8: CUSTO ANUAL PJ | E8: =SUM(E4:E7) -> 319080.2 | F8: Pode manter o custo atual ou simular outro
A9: Carro / allowance | B9: 0 | C9: R$/mês | D9: CUSTO MENSAL EQUIVALENTE | E9: =E8/12 -> 26590.017 | F9: Se aplicável
A10: Outros benefícios | B10: 0 | C10: R$/mês | D10: ECONOMIA ANUAL vs. atual | E10: =Cenarios!B11-E8 -> 12791.2 | F10: Seguro, celular, combustível etc.
A11: Bônus anual | B11: 0 | C11: R$/ano | D11: ECONOMIA % vs. atual | E11: =E10/Cenarios!B11 -> 0.03854264 | F11: Valor anual esperado
A14: Indicadores de negociação
A15: Indicador | B15: Resultado | C15: Unidade | D15: Interpretação
A16: Custo anual atual da empresa | B16: =Cenarios!B11 -> 331871.4 | C16: R$/ano | D16: Base de comparação
A17: Custo mensal equivalente atual | B17: =Cenarios!B12 -> 27655.95 | C17: R$/mês | D17: Custo anual ÷ 12
A18: Fee mensal PJ máximo para igualar custo atual | B18: =(Cenarios!B11-((B7+B8+B9+B10)*12)-B11)/(B5+B6) -> 24991.938 | C18: R$/mês | D18: Com as premissas do simulador

Sheet Fontes
A1: Fontes e notas metodológicas
A3: Tema | B3: Fonte | C3: Link / referência | D3: Nota
A4: Dados salariais | B4: Holerite março/2026 | C4: Arquivo enviado pelo usuário | D4: Salário bruto, FGTS, descontos, saúde e odontológico
A5: Remuneração adicional | B5: Informação do usuário | C5: Conversa atual | D5: R$ 8.675,00 por mês
A6: Simples Nacional / CPP | B6: Receita Federal | C6: https://www.gov.br/receitafederal/pt-br/assuntos/orientacao-tributaria/cobrancas-e-intimacoes/contribuicao-previdenciaria-anexo-iv-do-simples-nacional | D6: Modelo assume CPP patronal dentro do DAS e não adiciona 20% fora do Simples
A7: FGTS | B7: Ministério do Trabalho / FGTS Digital | C7: https://www.gov.br/trabalho-e-emprego/pt-br/servicos/empregador/fgtsdigital/perguntas-frequentes | D7: FGTS considerado a 8%
A8: Metodologia | B8: Modelo de negociação | C8: Cálculo interno | D8: Sem provisões mensais; custo anual efetivo convertido em média mensal
A10: Importante
A11: Este arquivo é um modelo gerencial para negociação e simulação, não um parecer contábil, tributário ou jurídico.
A12: Os valores de benefícios refletem o holerite analisado e podem mudar por reajustes ou condições do plano.
A13: No simulador, células amarelas/azuis são editáveis; fórmulas ficam em preto.
A15: Fontes — aba INSS x Investimento
A16: INSS 2026 | B16: Instituto Nacional do Seguro Social | C16: https://www.gov.br/inss/pt-br/direitos-e-deveres/inscricao-e-contribuicao/tabela-de-contribuicao-mensal | D16: Salário mínimo, teto RGPS e referência de contribuição
A17: IRPF 2026 | B17: Receita Federal | C17: https://www.gov.br/receitafederal/pt-br/assuntos/meu-imposto-de-renda/tabelas/2026 | D17: Tabela progressiva, desconto simplificado e redução mensal
A18: Dados previdenciários | B18: Meu INSS | C18: simulacao.pdf | D18: Idade, carência e tempo de contribuição
A19: Histórico contributivo | B19: CNIS | C19: extrato.pdf | D19: Remunerações e histórico de vínculos

Sheet INSS x Investimento
A1: INSS x Investimento Privado — comparação de estratégias
A2: Modelo de planejamento em valores reais de 2026. A aposentadoria incremental é uma aproximação para comparação, não uma simulação oficial do INSS.
A4: Premissas editáveis | F4: Premissas derivadas
A5: Premissa | B5: Valor | C5: Unidade | D5: Observação | F5: Indicador | G5: Valor | H5: Unidade | I5: Fórmula / leitura
A6: Idade atual | B6: 49.63 | C6: anos | D6: Simulação INSS em 28/09/2026: 49 anos, 7 meses e 18 dias | F6: Meses até aposentadoria | G6: =ROUND((B7-B6)*12,0) -> 184 | H6: meses | I6: (idade-alvo − idade atual) × 12
A7: Idade-alvo para aposentadoria | B7: 65 | C7: anos | D7: Altere para testar outra idade | F7: Anos futuros de contribuição | G7: =G6/12 -> 15.333333 | H7: anos | I7: Meses futuros ÷ 12
A8: Tempo de contribuição atual | B8: 22.86 | C8: anos | D8: Aprox. 22 anos, 10 meses e 13 dias | F8: Tempo total projetado aos 65 | G8: =B8+G7 -> 38.193333 | H8: anos | I8: Tempo atual + futuro
A9: Meses históricos na média desde 07/1994 | B9: 273 | C9: meses | D9: Estimativa a partir do CNIS / carência atual | F9: Coeficiente estimado do benefício | G9: =MIN(1,0.6+0.02*MAX(0,G8-20)) -> 0.96386667 | H9: % | I9: 60% + 2 p.p. por ano acima de 20, limitado a 100%
A10: Pró-labore mínimo de referência | B10: 1621 | C10: R$/mês | D10: Salário mínimo de 2026 | F10: Meses de aposentadoria até expectativa de vida | G10: =MAX(0,ROUND((B14-B7)*12,0)) -> 240 | H10: meses | I10: Expectativa de vida − idade de aposentadoria
A11: Alíquota INSS sobre pró-labore | B11: 0.11 | C11: % | D11: Hipótese: retenção de 11% do contribuinte individual | F11: Taxa real mensal do investimento | G11: =(1+B13)^(1/12)-1 -> 0.0040741238 | H11: % a.m. | I11: Equivalente mensal da rentabilidade real anual
A12: Teto previdenciário | B12: 8475.55 | C12: R$/mês | D12: Teto RGPS 2026
A13: Rentabilidade real anual do investimento | B13: 0.05 | C13: % a.a. | D13: Retorno acima da inflação; alterável
A14: Expectativa de vida para projeção | B14: 85 | C14: anos | D14: Usada para estimar renda mensal do patrimônio
A15: Desconto simplificado mensal IRPF | B15: 607.2 | C15: R$/mês | D15: Tabela IRPF 2026
A18: Comparação de estratégias de pró-labore
A19: Estratégia | B19: Pró-labore | C19: INSS mensal | D19: IRPF mensal | E19: Custo tributário PF | F19: Custo adicional vs. mínimo | G19: Investimento mensal se ficar no mínimo | H19: Patrimônio aos 65 | I19: Aumento estimado da aposentadoria | J19: Renda mensal do patrimônio até expectativa de vida | K19: Idade de equilíbrio simples | L19: Base previdenciária | M19: Fator de peso futuro | N19: Observação
A20: Mínimo | B20: 1621 | C20: =MIN(B20,$B$12)*$B$11 -> 178.31 | D20: =MAX(0,(0.075*MIN(MAX(MAX(0,B20-MAX(C20,$B$15))-2428.8,0),397.85)+0.15*MIN(MAX(MAX(0,B20-MAX(C20,$B$15))-2826.65,0),924.4)+0.225*MIN(MAX(MAX(0,B20-MAX(C20,$B$15))-3751.05,0),913.63)+0.275*MAX(MAX(0,B20-MAX(C20,$B$15))-4664.68,0))-MAX(0,978.62-0.133145*B20)) -> 0 | E20: =C20+D20 -> 178.31 | F20: =MAX(0,E20-$E$20) -> 0 | G20: =F20 -> 0 | H20: =G20*((1+MAX($G$11,0.000000001))^$G$6-1)/MAX($G$11,0.000000001) -> 0 | I20: =MAX(0,$G$9*($G$6/($B$9+$G$6))*(MIN(B20,$B$12)-$B$10)) -> 0 | J20: =H20*MAX($G$11,0.000000001)/(1-(1+MAX($G$11,0.000000001))^(-MAX($G$10,1))) -> 0 | K20: - | L20: =MIN(B20,$B$12) -> 1621 | M20: =$G$6/($B$9+$G$6) -> 0.40262582 | N20: Referência de menor custo atual
A21: Moderado 1 | B21: 4000 | C21: =MIN(B21,$B$12)*$B$11 -> 440 | D21: =MAX(0,(0.075*MIN(MAX(MAX(0,B21-MAX(C21,$B$15))-2428.8,0),397.85)+0.15*MIN(MAX(MAX(0,B21-MAX(C21,$B$15))-2826.65,0),924.4)+0.225*MIN(MAX(MAX(0,B21-MAX(C21,$B$15))-3751.05,0),913.63)+0.275*MAX(MAX(0,B21-MAX(C21,$B$15))-4664.68,0))-MAX(0,978.62-0.133145*B21)) -> 0 | E21: =C21+D21 -> 440 | F21: =MAX(0,E21-$E$20) -> 261.69 | G21: =F21 -> 261.69 | H21: =G21*((1+MAX($G$11,0.000000001))^$G$6-1)/MAX($G$11,0.000000001) -> 71491.422 | I21: =MAX(0,$G$9*($G$6/($B$9+$G$6))*(MIN(B21,$B$12)-$B$10)) -> 923.23663 | J21: =H21*MAX($G$11,0.000000001)/(1-(1+MAX($G$11,0.000000001))^(-MAX($G$10,1))) -> 467.43699 | K21: =$B$7+H21/(MAX(I21,0.01)*12) -> 71.45297 | L21: =MIN(B21,$B$12) -> 4000 | M21: =$G$6/($B$9+$G$6) -> 0.40262582 | N21: Faixa sem IRPF mensal pela redução de 2026
A22: Moderado 2 | B22: 6000 | C22: =MIN(B22,$B$12)*$B$11 -> 660 | D22: =MAX(0,(0.075*MIN(MAX(MAX(0,B22-MAX(C22,$B$15))-2428.8,0),397.85)+0.15*MIN(MAX(MAX(0,B22-MAX(C22,$B$15))-2826.65,0),924.4)+0.225*MIN(MAX(MAX(0,B22-MAX(C22,$B$15))-3751.05,0),913.63)+0.275*MAX(MAX(0,B22-MAX(C22,$B$15))-4664.68,0))-MAX(0,978.62-0.133145*B22)) -> 380.0285 | E22: =C22+D22 -> 1040.0285 | F22: =MAX(0,E22-$E$20) -> 861.7185 | G22: =F22 -> 861.7185 | H22: =G22*((1+MAX($G$11,0.000000001))^$G$6-1)/MAX($G$11,0.000000001) -> 235413.97 | I22: =MAX(0,$G$9*($G$6/($B$9+$G$6))*(MIN(B22,$B$12)-$B$10)) -> 1699.3918 | J22: =H22*MAX($G$11,0.000000001)/(1-(1+MAX($G$11,0.000000001))^(-MAX($G$10,1))) -> 1539.2224 | K22: =$B$7+H22/(MAX(I22,0.01)*12) -> 76.54403 | L22: =MIN(B22,$B$12) -> 6000 | M22: =$G$6/($B$9+$G$6) -> 0.40262582 | N22: Mais INSS + IRPF; ainda abaixo da faixa de R$ 7.350
A23: Faixa IRPF 2026 | B23: 7350 | C23: =MIN(B23,$B$12)*$B$11 -> 808.5 | D23: =MAX(0,(0.075*MIN(MAX(MAX(0,B23-MAX(C23,$B$15))-2428.8,0),397.85)+0.15*MIN(MAX(MAX(0,B23-MAX(C23,$B$15))-2826.65,0),924.4)+0.225*MIN(MAX(MAX(0,B23-MAX(C23,$B$15))-3751.05,0),913.63)+0.275*MAX(MAX(0,B23-MAX(C23,$B$15))-4664.68,0))-MAX(0,978.62-0.133145*B23)) -> 890.18675 | E23: =C23+D23 -> 1698.6868 | F23: =MAX(0,E23-$E$20) -> 1520.3768 | G23: =F23 -> 1520.3768 | H23: =G23*((1+MAX($G$11,0.000000001))^$G$6-1)/MAX($G$11,0.000000001) -> 415353.65 | I23: =MAX(0,$G$9*($G$6/($B$9+$G$6))*(MIN(B23,$B$12)-$B$10)) -> 2223.2966 | J23: =H23*MAX($G$11,0.000000001)/(1-(1+MAX($G$11,0.000000001))^(-MAX($G$10,1))) -> 2715.7336 | K23: =$B$7+H23/(MAX(I23,0.01)*12) -> 80.568235 | L23: =MIN(B23,$B$12) -> 7350 | M23: =$G$6/($B$9+$G$6) -> 0.40262582 | N23: Fim da redução de IRPF em 2026
A24: Teto RGPS | B24: 8475.55 | C24: =MIN(B24,$B$12)*$B$11 -> 932.3105 | D24: =MAX(0,(0.075*MIN(MAX(MAX(0,B24-MAX(C24,$B$15))-2428.8,0),397.85)+0.15*MIN(MAX(MAX(0,B24-MAX(C24,$B$15))-2826.65,0),924.4)+0.225*MIN(MAX(MAX(0,B24-MAX(C24,$B$15))-3751.05,0),913.63)+0.275*MAX(MAX(0,B24-MAX(C24,$B$15))-4664.68,0))-MAX(0,978.62-0.133145*B24)) -> 1165.6694 | E24: =C24+D24 -> 2097.9799 | F24: =MAX(0,E24-$E$20) -> 1919.6699 | G24: =F24 -> 1919.6699 | H24: =G24*((1+MAX($G$11,0.000000001))^$G$6-1)/MAX($G$11,0.000000001) -> 524437.04 | I24: =MAX(0,$G$9*($G$6/($B$9+$G$6))*(MIN(B24,$B$12)-$B$10)) -> 2660.0974 | J24: =H24*MAX($G$11,0.000000001)/(1-(1+MAX($G$11,0.000000001))^(-MAX($G$10,1))) -> 3428.9606 | K24: =$B$7+H24/(MAX(I24,0.01)*12) -> 81.42913 | L24: =MIN(B24,$B$12) -> 8475.55 | M24: =$G$6/($B$9+$G$6) -> 0.40262582 | N24: Maior base possível no RGPS em 2026
A25: Personalizado | B25: 5000 | C25: =MIN(B25,$B$12)*$B$11 -> 550 | D25: =MAX(0,(0.075*MIN(MAX(MAX(0,B25-MAX(C25,$B$15))-2428.8,0),397.85)+0.15*MIN(MAX(MAX(0,B25-MAX(C25,$B$15))-2826.65,0),924.4)+0.225*MIN(MAX(MAX(0,B25-MAX(C25,$B$15))-3751.05,0),913.63)+0.275*MAX(MAX(0,B25-MAX(C25,$B$15))-4664.68,0))-MAX(0,978.62-0.133145*B25)) -> 0 | E25: =C25+D25 -> 550 | F25: =MAX(0,E25-$E$20) -> 371.69 | G25: =F25 -> 371.69 | H25: =G25*((1+MAX($G$11,0.000000001))^$G$6-1)/MAX($G$11,0.000000001) -> 101542.46 | I25: =MAX(0,$G$9*($G$6/($B$9+$G$6))*(MIN(B25,$B$12)-$B$10)) -> 1311.3142 | J25: =H25*MAX($G$11,0.000000001)/(1-(1+MAX($G$11,0.000000001))^(-MAX($G$10,1))) -> 663.92164 | K25: =$B$7+H25/(MAX(I25,0.01)*12) -> 71.45297 | L25: =MIN(B25,$B$12) -> 5000 | M25: =$G$6/($B$9+$G$6) -> 0.40262582 | N25: Edite o pró-labore para testar qualquer valor
A28: Leitura para decisão
A29: Indicador | B29: Mínimo | C29: Personalizado | D29: Leitura | F29: Importante
A30: Pró-labore | B30: =B20 -> 1621 | C30: =B25 -> 5000 | D30: Base mensal escolhida para contribuição | F30: Este modelo isola a decisão previdenciária/pessoal. Não inclui eventual economia de DAS pelo Fator R, nem mudanças futuras nas regras do RGPS, no teto, no salário mínimo, na tabela do IRPF ou na tributação de dividendos. A estimativa de aposentadoria incremental usa o peso das futuras contribuições na média contributiva e o coeficiente projetado; serve para comparação entre cenários, não para requerimento de benefício.
A31: Custo tributário PF | B31: =E20 -> 178.31 | C31: =E25 -> 550 | D31: INSS + IRPF mensal
A32: Patrimônio privado aos 65 | B32: =H20 -> 0 | C32: =H25 -> 101542.46 | D32: Se a diferença tributária for investida com a rentabilidade real assumida
A33: Aumento estimado da aposentadoria | B33: =I20 -> 0 | C33: =I25 -> 1311.3142 | D33: Diferença mensal estimada de benefício versus contribuir pelo mínimo
A34: Idade de equilíbrio simples | B34: =K20 -> - | C34: =K25 -> 71.45297 | D34: Idade em que o INSS adicional acumulado igualaria o capital privado; ignora rendimento após a aposentadoria
A37: Fontes utilizadas nesta aba
A38: Tema | B38: Fonte | C38: URL / documento | D38: Uso no modelo
A39: Idade, carência e tempo de contribuição | B39: Simulação de Aposentadoria - Meu INSS | C39: Arquivo simulacao.pdf enviado em 28/09/2026 | D39: Idade e tempo de contribuição atuais
A40: Histórico contributivo | B40: CNIS - Extrato Previdenciário | C40: Arquivo extrato.pdf enviado em 28/09/2026 | D40: Histórico desde 1993 e teto consolidado em 2026
A41: INSS 2026 | B41: INSS | C41: https://www.gov.br/inss/pt-br/direitos-e-deveres/inscricao-e-contribuicao/tabela-de-contribuicao-mensal | D41: Salário mínimo e teto RGPS de 2026
A42: IRPF 2026 | B42: Receita Federal | C42: https://www.gov.br/receitafederal/pt-br/assuntos/meu-imposto-de-renda/tabelas/2026 | D42: Tabela progressiva, desconto simplificado e redução mensal
A43: Metodologia previdenciária | B43: Modelo comparativo | C43: Cálculo aproximado | D43: Compara benefício incremental versus patrimônio privado em valores reais
